["{\n   \"name\": \"Bitcoin\",\n   \"price\": \"$458.55\",\n   \"supply\": \"15,469,750\"\n}", "{\n   \"name\": \"Ethereum\",\n   \"price\": \"$8.00\",\n   \"supply\": \"79,395,862\"\n}", "{\n   \"name\": \"XRP\",\n   \"price\": \"$0.007251\",\n   \"supply\": \"34,868,679,462\"\n}", "{\n   \"name\": \"Litecoin\",\n   \"price\": \"$3.63\",\n   \"supply\": \"45,498,576\"\n}", "{\n   \"name\": \"Dash\",\n   \"price\": \"$6.44\",\n   \"supply\": \"6,398,319\"\n}", "{\n   \"name\": \"MaidSafeCoin\",\n   \"price\": \"$0.07034\",\n   \"supply\": \"452,552,412\"\n}", "{\n   \"name\": \"Dogecoin\",\n   \"price\": \"$0.0002267\",\n   \"supply\": \"104,057,607,362\"\n}", "{\n   \"name\": \"NEM\",\n   \"price\": \"$0.001533\",\n   \"supply\": \"8,999,999,999\"\n}", "{\n   \"name\": \"Monero\",\n   \"price\": \"$1.01\",\n   \"supply\": \"11,692,187\"\n}", "{\n   \"name\": \"Factom\",\n   \"price\": \"$1.30\",\n   \"supply\": \"8,753,219\"\n}", "{\n   \"name\": \"BitShares\",\n   \"price\": \"$0.004116\",\n   \"supply\": \"2,553,280,000\"\n}", "{\n   \"name\": \"Stellar\",\n   \"price\": \"$0.001912\",\n   \"supply\": \"5,485,679,598\"\n}", "{\n   \"name\": \"Peercoin\",\n   \"price\": \"$0.4417\",\n   \"supply\": \"23,124,802\"\n}", "{\n   \"name\": \"HyperSpace\",\n   \"price\": \"$0.05513\",\n   \"supply\": \"184,800,000\"\n}", "{\n   \"name\": \"Feathercoin\",\n   \"price\": \"$0.0655\",\n   \"supply\": \"148,407,000\"\n}", "{\n   \"name\": \"Emercoin\",\n   \"price\": \"$0.2188\",\n   \"supply\": \"37,570,233\"\n}", "{\n   \"name\": \"FedoraCoin\",\n   \"price\": \"$0.0000177\",\n   \"supply\": \"420,069,802,180\"\n}", "{\n   \"name\": \"Nxt\",\n   \"price\": \"$0.007063\",\n   \"supply\": \"999,997,096\"\n}", "{\n   \"name\": \"Bytecoin\",\n   \"price\": \"$0.00003689\",\n   \"supply\": \"179,931,057,367\"\n}", "{\n   \"name\": \"Namecoin\",\n   \"price\": \"$0.454\",\n   \"supply\": \"14,147,300\"\n}"]