["{\n   \"name\": \"Bitcoin\",\n   \"price\": \"$38,903.44\",\n   \"supply\": \"18,622,487\"\n}", "{\n   \"name\": \"Ethereum\",\n   \"price\": \"$1,614.23\",\n   \"supply\": \"114,578,160\"\n}", "{\n   \"name\": \"Tether\",\n   \"price\": \"$1.00\",\n   \"supply\": \"28,606,332,458\"\n}", "{\n   \"name\": \"Cardano\",\n   \"price\": \"$0.6632\",\n   \"supply\": \"31,112,484,646\"\n}", "{\n   \"name\": \"XRP\",\n   \"price\": \"$0.418\",\n   \"supply\": \"45,404,028,640\"\n}", "{\n   \"name\": \"Polkadot\",\n   \"price\": \"$19.79\",\n   \"supply\": \"908,009,247\"\n}", "{\n   \"name\": \"Binance Coin\",\n   \"price\": \"$68.59\",\n   \"supply\": \"154,532,785\"\n}", "{\n   \"name\": \"Chainlink\",\n   \"price\": \"$24.79\",\n   \"supply\": \"405,509,556\"\n}", "{\n   \"name\": \"Litecoin\",\n   \"price\": \"$151.14\",\n   \"supply\": \"66,436,829\"\n}", "{\n   \"name\": \"Dogecoin\",\n   \"price\": \"$0.07878\",\n   \"supply\": \"128,275,738,389\"\n}", "{\n   \"name\": \"Stellar\",\n   \"price\": \"$0.3835\",\n   \"supply\": \"22,324,934,033\"\n}", "{\n   \"name\": \"Bitcoin Cash\",\n   \"price\": \"$445.17\",\n   \"supply\": \"18,648,713\"\n}", "{\n   \"name\": \"USD Coin\",\n   \"price\": \"$0.9999\",\n   \"supply\": \"6,440,407,860\"\n}", "{\n   \"name\": \"Aave\",\n   \"price\": \"$461.51\",\n   \"supply\": \"12,350,857\"\n}", "{\n   \"name\": \"Uniswap\",\n   \"price\": \"$18.69\",\n   \"supply\": \"300,918,579\"\n}", "{\n   \"name\": \"Wrapped Bitcoin\",\n   \"price\": \"$38,877.48\",\n   \"supply\": \"121,625\"\n}", "{\n   \"name\": \"Bitcoin SV\",\n   \"price\": \"$183.06\",\n   \"supply\": \"18,646,552\"\n}", "{\n   \"name\": \"EOS\",\n   \"price\": \"$3.44\",\n   \"supply\": \"950,348,329\"\n}", "{\n   \"name\": \"Cosmos\",\n   \"price\": \"$13.92\",\n   \"supply\": \"210,028,496\"\n}", "{\n   \"name\": \"NEM\",\n   \"price\": \"$0.3052\",\n   \"supply\": \"8,999,999,999\"\n}"]