["{\n   \"name\": \"Bitcoin\",\n   \"price\": \"$593.85\",\n   \"supply\": \"13,069,400\"\n}", "{\n   \"name\": \"Litecoin\",\n   \"price\": \"$7.75\",\n   \"supply\": \"30,601,804\"\n}", "{\n   \"name\": \"XRP\",\n   \"price\": \"$0.006021\",\n   \"supply\": \"8,252,600,832\"\n}", "{\n   \"name\": \"Nxt\",\n   \"price\": \"$0.04492\",\n   \"supply\": \"999,997,120\"\n}", "{\n   \"name\": \"Dash\",\n   \"price\": \"$5.83\",\n   \"supply\": \"4,508,122\"\n}", "{\n   \"name\": \"Peercoin\",\n   \"price\": \"$1.16\",\n   \"supply\": \"21,589,386\"\n}", "{\n   \"name\": \"Dogecoin\",\n   \"price\": \"$0.0002169\",\n   \"supply\": \"88,400,330,752\"\n}", "{\n   \"name\": \"BitShares\",\n   \"price\": \"$0.0082\",\n   \"supply\": \"1,999,775,104\"\n}", "{\n   \"name\": \"Namecoin\",\n   \"price\": \"$1.58\",\n   \"supply\": \"9,446,450\"\n}", "{\n   \"name\": \"MaidSafeCoin\",\n   \"price\": \"$0.02821\",\n   \"supply\": \"452,552,416\"\n}", "{\n   \"name\": \"BlackCoin\",\n   \"price\": \"$0.1025\",\n   \"supply\": \"74,635,480\"\n}", "{\n   \"name\": \"Monero\",\n   \"price\": \"$2.55\",\n   \"supply\": \"2,390,274\"\n}", "{\n   \"name\": \"BitShares PTS\",\n   \"price\": \"$3.68\",\n   \"supply\": \"1,654,454\"\n}", "{\n   \"name\": \"Counterparty\",\n   \"price\": \"$2.16\",\n   \"supply\": \"2,648,957\"\n}", "{\n   \"name\": \"ReddCoin\",\n   \"price\": \"$0.0002019\",\n   \"supply\": \"26,853,961,728\"\n}", "{\n   \"name\": \"CloakCoin\",\n   \"price\": \"$0.9397\",\n   \"supply\": \"4,518,632\"\n}", "{\n   \"name\": \"XCurrency\",\n   \"price\": \"$0.7635\",\n   \"supply\": \"5,520,165\"\n}", "{\n   \"name\": \"Omni\",\n   \"price\": \"$7.00\",\n   \"supply\": \"563,162\"\n}", "{\n   \"name\": \"Quark\",\n   \"price\": \"$0.01255\",\n   \"supply\": \"248,060,928\"\n}", "{\n   \"name\": \"VeriCoin\",\n   \"price\": \"$0.1012\",\n   \"supply\": \"26,800,860\"\n}"]